mlstm_kernels/__init__.py
mlstm_kernels/baselines/__init__.py
mlstm_kernels/baselines/flash_attention/__init__.py
mlstm_kernels/baselines/flash_attention/flash_attention_triton.py
mlstm_kernels/baselines/flash_attention/torch_sdp_attention.py
mlstm_kernels/baselines/flash_attention/triton_tutorial.py
mlstm_kernels/baselines/flash_linear_attention/__init__.py
mlstm_kernels/baselines/flash_linear_attention/fla_utils.py
mlstm_kernels/baselines/flash_linear_attention/gla/__init__.py
mlstm_kernels/baselines/flash_linear_attention/gla/chunk.py
mlstm_kernels/baselines/flash_linear_attention/gla/chunk_fuse.py
mlstm_kernels/baselines/flash_linear_attention/gla/chunk_util.py
mlstm_kernels/baselines/flash_linear_attention/gla/naive.py
mlstm_kernels/baselines/flash_linear_attention/gla/recurrent_fuse.py
mlstm_kernels/baselines/flash_linear_attention/simple_gla/__init__.py
mlstm_kernels/baselines/flash_linear_attention/simple_gla/chunk.py
mlstm_kernels/baselines/flash_linear_attention/simple_gla/naive.py
mlstm_kernels/baselines/lightning_attention/__init__.py
mlstm_kernels/baselines/lightning_attention/lightning_attn2.py
mlstm_kernels/baselines/lightning_attention/utils.py
mlstm_kernels/jax/__init__.py
mlstm_kernels/jax/stride_utils.py
mlstm_kernels/jax/utils.py
mlstm_kernels/jax/xla_utils.py
mlstm_kernels/jax/chunkwise/__init__.py
mlstm_kernels/jax/chunkwise/native/__init__.py
mlstm_kernels/jax/chunkwise/native/fw.py
mlstm_kernels/jax/chunkwise/native/fwbw.py
mlstm_kernels/jax/chunkwise/triton_limit_chunk/__init__.py
mlstm_kernels/jax/chunkwise/triton_limit_chunk/bw.py
mlstm_kernels/jax/chunkwise/triton_limit_chunk/bw_parallel.py
mlstm_kernels/jax/chunkwise/triton_limit_chunk/bw_recurrent.py
mlstm_kernels/jax/chunkwise/triton_limit_chunk/fw.py
mlstm_kernels/jax/chunkwise/triton_limit_chunk/fw_parallel.py
mlstm_kernels/jax/chunkwise/triton_limit_chunk/fw_recurrent.py
mlstm_kernels/jax/chunkwise/triton_limit_chunk/fwbw.py
mlstm_kernels/jax/chunkwise/triton_xl_chunk/__init__.py
mlstm_kernels-2.0.2.dist-info/licenses/LICENSE
mlstm_kernels-2.0.2.dist-info/METADATA
mlstm_kernels-2.0.2.dist-info/WHEEL
mlstm_kernels-2.0.2.dist-info/top_level.txt
mlstm_kernels-2.0.2.dist-info/RECORD
