Metadata-Version: 2.4
Name: mlstm_kernels
Version: 2.0.2
Summary: A library providing fast and efficient mLSTM kernels for the xLSTM.
Author-email: Maximilian Beck <beck@ml.jku.at>, Korbinian Poeppel <poeppel@ml.jku.at>, Phillip Lippe <phillip.lippe@gmail.com>, Sebastian Boeck <sebastian.boeck@nx-ai.com>
License: NXAI COMMUNITY LICENSE AGREEMENT
Keywords: mLSTM,xLSTM,LSTM,Transformer,Machine Learning,Deep Learning,State Space Models
Classifier: Programming Language :: Python :: 3
Classifier: Operating System :: OS Independent
Requires-Python: >=3.11
License-File: LICENSE
Requires-Dist: dacite
Requires-Dist: einops
Requires-Dist: ipykernel
Requires-Dist: matplotlib
Requires-Dist: numpy
Requires-Dist: omegaconf
Requires-Dist: rich
Requires-Dist: torch
Requires-Dist: tqdm
Dynamic: license-file
